README.md
setup.py
test/test.py
waveglow_vocoder/__init__.py
waveglow_vocoder/audio_layers.py
waveglow_vocoder/config.json
waveglow_vocoder/glow.py
waveglow_vocoder/version.py
waveglow_vocoder/vocoder.py
waveglow_vocoder.egg-info/PKG-INFO
waveglow_vocoder.egg-info/SOURCES.txt
waveglow_vocoder.egg-info/dependency_links.txt
waveglow_vocoder.egg-info/requires.txt
waveglow_vocoder.egg-info/top_level.txt