Metadata-Version: 2.1
Name: waveglow-vocoder
Version: 0.1.2
Summary: A vocoder that can convert audio to Mel-Spectrogram and reverse with WaveGlow, all on GPU(if avaliable).
Home-page: http://github.com/HudsonHuang/waveglow_vocoder
Author: HudsonHuang
Author-email: 790209714@qq.com
License: BSD-3
Keywords: deep learning,audio processing,machine learning
Platform: UNKNOWN
Classifier: License :: OSI Approved :: BSD License
Classifier: Programming Language :: Python
Classifier: Development Status :: 3 - Alpha
Classifier: Intended Audience :: Developers
Classifier: Topic :: Multimedia :: Sound/Audio :: Analysis
Classifier: Programming Language :: Python :: 2
Classifier: Programming Language :: Python :: 2.7
Classifier: Programming Language :: Python :: 3
Classifier: Programming Language :: Python :: 3.4
Classifier: Programming Language :: Python :: 3.5
Classifier: Programming Language :: Python :: 3.6
Classifier: Programming Language :: Python :: 3.7
Classifier: Programming Language :: Python :: 3.8
